doc_ufcn/__init__.py
doc_ufcn/image.py
doc_ufcn/main.py
doc_ufcn/model.py
doc_ufcn/models.py
doc_ufcn/prediction.py
doc_ufcn/utils.py
doc_ufcn/train/__init__.py
doc_ufcn/train/cli.py
doc_ufcn/train/configuration.py
doc_ufcn/train/evaluate.py
doc_ufcn/train/experiment.py
doc_ufcn/train/mask.py
doc_ufcn/train/mlflow_utils.py
doc_ufcn/train/normalization_params.py
doc_ufcn/train/predict.py
doc_ufcn/train/training.py
doc_ufcn/train/utils/__init__.py
doc_ufcn/train/utils/evaluation.py
doc_ufcn/train/utils/object_metrics.py
doc_ufcn/train/utils/pixel_metrics.py
doc_ufcn/train/utils/prediction.py
doc_ufcn/train/utils/preprocessing.py
doc_ufcn/train/utils/training.py
doc_ufcn/train/utils/training_pixel_metrics.py
hugging_face/__init__.py
hugging_face/app.py
hugging_face/config.py
hugging_face/tools.py
doc_ufcn-0.1.9.dist-info/LICENSE
doc_ufcn-0.1.9.dist-info/METADATA
doc_ufcn-0.1.9.dist-info/WHEEL
doc_ufcn-0.1.9.dist-info/top_level.txt
doc_ufcn-0.1.9.dist-info/RECORD
