Metadata-Version: 2.1
Name: doc-ufcn
Version: 0.1.9
Summary: Doc-UFCN
Home-page: https://gitlab.com/teklia/dla/doc-ufcn
Author: Mélodie Boillet
Author-email: boillet@teklia.com
Project-URL: Source, https://gitlab.teklia.com/dla/doc-ufcn/
Project-URL: Tracker, https://gitlab.teklia.com/dla/doc-ufcn/issues/
Classifier: Development Status :: 5 - Production/Stable
Classifier: Programming Language :: Python :: 3 :: Only
Classifier: Programming Language :: Python :: 3.10
Classifier: Topic :: Scientific/Engineering :: Artificial Intelligence
Classifier: Topic :: Scientific/Engineering :: Image Recognition
Requires-Python: >= 3.10, < 3.11
License-File: LICENSE
Requires-Dist: huggingface-hub ==0.19.0
Requires-Dist: numpy ==1.26.2
Requires-Dist: opencv-python-headless ==4.7.0.72
Requires-Dist: pyyaml ==6.0.1
Requires-Dist: requests <3,>=2
Requires-Dist: teklia-toolbox ==0.1.3
Requires-Dist: torch ==2.1.0
Provides-Extra: training
Requires-Dist: imageio ==2.27.0 ; extra == 'training'
Requires-Dist: matplotlib ==3.8.1 ; extra == 'training'
Requires-Dist: mlflow ==2.2.1 ; extra == 'training'
Requires-Dist: Shapely ==2.0.2 ; extra == 'training'
Requires-Dist: teklia-toolbox ==0.1.3 ; extra == 'training'
Requires-Dist: tensorboard ==2.15.1 ; extra == 'training'
Requires-Dist: torchvision ==0.16.0 ; extra == 'training'
Requires-Dist: tqdm ==4.66.1 ; extra == 'training'
